inference/__init__.py
mlopspython_inference-9685412409802298096004.dist-info/METADATA
mlopspython_inference-9685412409802298096004.dist-info/WHEEL
mlopspython_inference-9685412409802298096004.dist-info/top_level.txt
mlopspython_inference-9685412409802298096004.dist-info/RECORD
