Metadata-Version: 2.1
Name: mlopspython-inference
Version: 9685412409802298096004
Summary: Inference package for MLOpsPython project
Home-page: https://github.com/guillaume-chervet/MLOpsPython
Author: Guillaume Chervet
Author-email: guillaume.chervet@gmail.com
Platform: POSIX
Classifier: Programming Language :: Python :: 3 :: Only
Classifier: Programming Language :: Python :: 3.11
Requires-Python: >=3.8
Requires-Dist: numpy (==1.23.5)
Requires-Dist: matplotlib (==3.7.0)
Requires-Dist: keras (==2.12.0rc0)
Requires-Dist: tensorflow (==2.12.0rc0)
Requires-Dist: opencv-contrib-python-headless (==4.7.0.68)
